transcendental/__init__.py
transcendental/config.py
transcendental/predict.py
transcendental/train.py
transcendental-0.5.5.data/data/etc/transcendental/models/model.h5
transcendental-0.5.5.data/data/etc/transcendental/models/model.yaml
transcendental-0.5.5.dist-info/METADATA
transcendental-0.5.5.dist-info/RECORD
transcendental-0.5.5.dist-info/WHEEL
transcendental-0.5.5.dist-info/entry_points.txt
transcendental-0.5.5.dist-info/pbr.json
transcendental-0.5.5.dist-info/top_level.txt
