Metadata-Version: 2.1
Name: transcendental
Version: 0.5.5
Summary: Minimal IA for image recognition
Home-page: https://github.com/4383/transcendental
Author: hervé beraud
Author-email: herveberaud.pro@gmail.com
License: UNKNOWN
Platform: UNKNOWN
Classifier: Development Status :: 2 - Pre-Alpha
Classifier: Intended Audience :: Information Technology
Classifier: License :: OSI Approved :: MIT License
Classifier: Operating System :: POSIX
Classifier: Programming Language :: Python
Classifier: Programming Language :: Python :: 2
Classifier: Programming Language :: Python :: 2.7
Classifier: Programming Language :: Python :: 3
Classifier: Programming Language :: Python :: 3.4
Classifier: Programming Language :: Python :: 3.5
Classifier: Programming Language :: Python :: 3.6
Requires: pbd
Provides-Extra: test
Provides-Extra: devel
Requires-Dist: keras (==2.1.6)
Requires-Dist: tensorflow (==1.8.0)
Requires-Dist: Pillow (==5.1.0)
Requires-Dist: h5py (==2.7.1)
Provides-Extra: devel
Requires-Dist: fixtures; extra == 'devel'
Requires-Dist: pbr; extra == 'devel'
Requires-Dist: tox; extra == 'devel'
Requires-Dist: sphinx; extra == 'devel'
Provides-Extra: test
Requires-Dist: fixtures; extra == 'test'
Requires-Dist: tox; extra == 'test'
